<annotation>
	<folder>my-project-name</folder>
	<filename>2A18BC755D723E5502227B785AF3F51E.jpg</filename>
	<path>/my-project-name/2A18BC755D723E5502227B785AF3F51E.jpg</path>
	<source>
		<database>Unspecified</database>
	</source>
	<size>
		<width>960</width>
		<height>720</height>
		<depth>3</depth>
	</size>
	<object>
		<name>Grain</name>
		<pose>Unspecified</pose>
		<truncated>0</truncated>
		<difficult>0</difficult>
		<bndbox>
			<xmin>102</xmin>
			<ymin>29</ymin>
			<xmax>915</xmax>
			<ymax>635</ymax>
		</bndbox>
	</object>
</annotation>